cubicweb_dataprocessing/__init__.py
cubicweb_dataprocessing/__pkginfo__.py
cubicweb_dataprocessing/entities.py
cubicweb_dataprocessing/hooks.py
cubicweb_dataprocessing/schema.py
cubicweb_dataprocessing/views.py
cubicweb_dataprocessing/workflows.py
cubicweb_dataprocessing-0.8.0.dist-info/METADATA
cubicweb_dataprocessing-0.8.0.dist-info/WHEEL
cubicweb_dataprocessing-0.8.0.dist-info/top_level.txt
cubicweb_dataprocessing-0.8.0.dist-info/RECORD
