Metadata-Version: 2.1
Name: cubicweb-dataprocessing
Version: 0.8.0
Summary: Data validation and transformation process
Home-page: http://www.cubicweb.org/project/cubicweb-dataprocessing
Author: LOGILAB S.A. (Paris, FRANCE)
Author-email: contact@logilab.fr
License: LGPL
Platform: UNKNOWN
Classifier: Environment :: Web Environment
Classifier: Framework :: CubicWeb
Classifier: Programming Language :: Python
Classifier: Programming Language :: Python :: 3
Classifier: Programming Language :: Python :: 3 :: Only
Classifier: Programming Language :: JavaScript
Requires-Dist: cubicweb (<3.39.0,>=3.38.0)
Requires-Dist: cubicweb-file
